pypiZXCA/__init__.py
pypiZXCA/test.py
pypiZXCA-0.0.1.dist-info/METADATA
pypiZXCA-0.0.1.dist-info/WHEEL
pypiZXCA-0.0.1.dist-info/top_level.txt
pypiZXCA-0.0.1.dist-info/RECORD
